{"a,.link":{"color":"#04700C"},"body":{"background":"#D0F8AA","color":"#04700C"},".playlists-tabs-li":{"background":"#B7DB9B"},".playlists-tabs-li.active":{"background":"#EAF1E5"},".playlist":{"background":"#FFF"},".playlist-item:nth-of-type(odd)":{"background":"#E0FCCC"},".playlist-item:nth-of-type(even)":{"background":"#ECFDDF"},".playlist-item.selected":{"background":"#6DAA41","color":"#fff"},".window":{"border-color":"#7ABD49"},"#preferences-tabs":{"border-color":"#B0E4B0","background":"#D5F8BB"},":root .preferences-item.active":{"background":"#B7DB9B","color":"#04700C"},"#find-window-results":{"color":"#04700C","background":"#EAF1E5"},"#window-title":{"background":"#7ABD49","color":"#fff"},"#window-buttons":{"border-color":"#B0E4B0","background":"#C9F0B6"},"#volume,#progress":{"background":"#EAF1E5"},"#volume-progress,#playback-progress":{"background":"#B7DB9B"},".add-item.active":{"background":"#fff","color":"#000"},".add-item span":{"color":"#358D35"},".add-item.active span":{"color":"#504848"},"h6":{"color":"#7ABD49"},"#console-title":{"background":"#C9F0B6","border-top-color":"#B0E4B0"},"#add-playlist":{"background":"#A0E771","border-color":"#D0F8AA"},"#window-content":{"background":"#E7FFD7"},".select select":{"background":"#fff"},".select.top-bar select":{"background":"#fff"},"#connected-table tr td:first-child":{"color":"#358D35"},"button,.button":{"background":"#fff"},"#keyboard-shortcuts button:not(#shortcut-add)":{"color":"#588337"},"#translation-contributors":{"background":"#C9F0B6"},"#init-search":{"background":"#E9EBE8"},"#window-close":{"color":"#fff"}}