{
  "body": {
    "color": "#fff",
    "background": "#81007f"
  },
  ".playlists-tabs-li": {
    "background": "#000"
  },
  ".playlists-tabs-li.active": {
    "background": "#fff",
    "color": "#000"
  },
  ".playlist": {
    "background": "#000"
  },
  ".playlist-item": {
    "color": "#fffd00"
  },
  ".playlist-item.selected": {
    "color": "#000",
    "background": "#fff"
  },
  ".window": {
    "border-color": "#00f"
  },
  "#preferences-tabs": {
    "border-color": "#fffd00",
    "background": "#fff"
  },
  ":root .preferences-item.active": {
    "color": "#000",
    "background": "#fffd00"
  },
  "#preference-general-help,#preference-language-help,.help-icon": {
    "color": "#fffd00"
  },
  "#window-title": {
    "background": "#00f"
  },
  "#window-buttons": {
    "border-color": "#fffd00",
    "background": "#fffd00"
  },
  "#volume,#progress": {
    "background": "#000"
  },
  ".add-item.active": {
    "background": "#fff",
    "color": "#000"
  },
  ".add-item span": {
    "color": "#fff"
  },
  ".add-item.active span": {
    "color": "#000"
  },
  "h6": {
    "color": "#fffd00"
  },
  "#console-title": {
    "background": "#fffd00",
    "border-top-color": "#fffd00"
  },
  "#add-playlist": {
    "background": "#fffd00",
    "border-color": "#81007f",
    "color": "#000"
  },
  "#window-content": {
    "color": "#fff",
    "background": "#000"
  },
  ".select:not(.top-bar)": {
    "color": "initial"
  },
  ".select select": {
    "background": "#fff"
  },
  ".top-bar select": {
    "background": "#fffd00"
  },
  "#connected-table tr td:first-child": {
    "color": "#fff"
  },
  "button,.button": {
    "background": "#fff"
  },
  "#translation-contributors": {
    "background": "#fffd00",
    "color": "#000"
  },
  ".playlists-tabs-li.active a,.menu-ul-li:hover": {
    "color": "#000"
  },
  "#drop-zone.hover": {
    "border-color": "#fffd00"
  },
  ".selected .item-queue:not(:empty)": {
    "color": "#fff"
  },
  ".favicon": {
    "background": "#fff"
  },
  "#find:focus": {
    "color": "#000"
  },
  "#find:focus ~ .empty-find-icon,#find:focus ~ .find-icon": {
    "color" : "#000"
  }
}